pydg1000z/__init__.py
pydg1000z/pydg1000z.py
pydg1000z-0.1.0.dist-info/LICENSE
pydg1000z-0.1.0.dist-info/METADATA
pydg1000z-0.1.0.dist-info/WHEEL
pydg1000z-0.1.0.dist-info/top_level.txt
pydg1000z-0.1.0.dist-info/RECORD
