Metadata-Version: 2.1
Name: pydg1000z
Version: 0.1.0
Summary: Rigol DG1000Z control library (unofficial)
Home-page: https://github.com/PMSchueler/pydg1000z
Author: P.M.Schueler
Author-email: peter.schueler@gmxpro.de
Classifier: Programming Language :: Python :: 3
Classifier: License :: OSI Approved :: MIT License
Classifier: Operating System :: OS Independent
Requires-Python: >=3.11
License-File: LICENSE
Requires-Dist: pylabdevs-tspspi >=0.0.15
